[
  {"code":"ehr_headcount_by_dept","name:zh-CN":"部门人数统计","name:en":"Headcount by Department","description":"Employee count by department for org chart.","purpose":"Provides headcount breakdown by department for HR dashboards.","parameter_schema":{"type":"object","properties":{"tenantId":{"type":"string","description":"Tenant ID (auto-injected)"}},"required":["tenantId"]},"fromSql":"SELECT ehr_em_department_id AS department_id, COUNT(*) AS headcount FROM mt_ehr_employee WHERE tenant_id = #{params.tenantId} AND ehr_em_status IN ('probation','active','on_leave') GROUP BY ehr_em_department_id ORDER BY headcount DESC","outputFields":[{"code":"department_id","searchable":true},{"code":"headcount","sortable":true}]},
  {"code":"ehr_payroll_summary","name:zh-CN":"薪资汇总","name:en":"Payroll Summary","description":"Monthly payroll totals.","purpose":"Provides aggregate payroll data for financial reporting.","parameter_schema":{"type":"object","properties":{"tenantId":{"type":"string","description":"Tenant ID (auto-injected)"},"period":{"type":"string","description":"Pay period (YYYY-MM)"}},"required":["tenantId"]},"fromSql":"SELECT ehr_pr_period AS period, COUNT(*) AS employee_count, COALESCE(SUM(ehr_pr_base_salary),0) AS total_base, COALESCE(SUM(ehr_pr_net_pay),0) AS total_net FROM mt_ehr_payroll WHERE tenant_id = #{params.tenantId} AND (#{params.period} IS NULL OR ehr_pr_period = #{params.period}) GROUP BY ehr_pr_period ORDER BY ehr_pr_period DESC","outputFields":[{"code":"period","searchable":true,"sortable":true},{"code":"employee_count","sortable":true},{"code":"total_base","sortable":true},{"code":"total_net","sortable":true}]}
]
